{
  "notes": [
    {
      "text": "note test",
      "date": "2021-02-10",
      "criminalId": "1",
      "id": 22
    },
    {
      "text": "yet another test",
      "date": "2021-02-10",
      "criminalId": "1",
      "id": 23
    },
    {
      "text": "do a note",
      "date": "2021-02-10",
      "criminalId": "1",
      "id": 24
    },
    {
      "text": "running agagi",
      "date": "2021-02-10",
      "criminalId": "1",
      "id": 25
    },
    {
      "text": "recreate",
      "date": "2021-02-10",
      "criminalId": "2",
      "id": 26
    }
  ]
}